{
" ": {
        "reason": "Contact for unban https://www.facebook.com/TERGETYOURID",
        "dateAdded": "05/12/2021 06:46:20"   
    },
" ": "",
" ": {
        "reason": "",
        "dateAdded": "05/12/2021 06:46:20"   
    },
" ": {
        "reason": "",
        "dateAdded": "05/12/2021 06:46:20"   
    },
" ": {
        "reason": "",
        "dateAdded": "05/12/2021 06:46:20"   
    },
" ": {
        "reason": "",
        "dateAdded": "07/14/2022 11:46:20" 
    },
" ": {
        "reason": "you will die of a thief",
        "dateAdded": "07/14/2022 11:46:20" 
    },
" ": {
        "reason": "MTX Mentality",
        "dateAdded": "05/12/2021 06:46:20"   
    },
" ": {
        "reason": "MTX Mentality",
        "dateAdded": "05/12/2023 06:46:20"   
    },
" ": {
        "reason": "MTX Mentality",
        "dateAdded": "05/02/2023 08:05:00"   
    },
" ": {
        "reason": "How dare you stole my file",
        "dateAdded": "01/02/2023 09:36:20"   
    },
" ": {
        "reason": "How dare you stole my file",
        "dateAdded": "01/01/2023 06:46:00"   
    }
}
